fastcom/__main__.py
fastcom/test.py
fastcom/timer.py
fastcom_cli-1.1.dist-info/LICENSE
fastcom_cli-1.1.dist-info/METADATA
fastcom_cli-1.1.dist-info/WHEEL
fastcom_cli-1.1.dist-info/entry_points.txt
fastcom_cli-1.1.dist-info/top_level.txt
fastcom_cli-1.1.dist-info/RECORD
