Metadata-Version: 2.1
Name: fastcom-cli
Version: 1.1
Summary: Unofficial CLI for fast.com
Project-URL: repo, https://github.com/Tina-otoge/fastcom-cli
License-File: LICENSE
Requires-Dist: requests
